eda_lucas-0.4.1.dist-info/METADATA
eda_lucas-0.4.1.dist-info/WHEEL
eda_lucas-0.4.1.dist-info/entry_points.txt
eda_lucas/__init__.py
eda_lucas/cli.py
eda_lucas-0.4.1.dist-info/RECORD
